aiourllib/__init__.py
aiourllib/api.py
aiourllib/exc.py
aiourllib/models.py
aiourllib/request.py
aiourllib/response.py
aiourllib/rfc2161.py
aiourllib/uri.py
aiourllib/utils.py
aiourllib-0.1.3.dist-info/DESCRIPTION.rst
aiourllib-0.1.3.dist-info/METADATA
aiourllib-0.1.3.dist-info/RECORD
aiourllib-0.1.3.dist-info/WHEEL
aiourllib-0.1.3.dist-info/metadata.json
aiourllib-0.1.3.dist-info/top_level.txt
