Metadata-Version: 1.1
Name: aiourllib
Version: 0.1.3
Summary: HTTP library for asyncio
Home-page: https://github.com/mylokin/aiourllib
Author: Andrey Gubarev
Author-email: mylokin@me.com
License: MIT
Keywords: http
Platform: any
Classifier: Development Status :: 4 - Beta
Classifier: Intended Audience :: Developers
Classifier: Operating System :: OS Independent
Classifier: License :: OSI Approved :: MIT License
Classifier: Programming Language :: Python :: 3.5
Classifier: Topic :: Internet :: WWW/HTTP
Classifier: Topic :: Software Development :: Libraries :: Python Modules
